verilog files/Anding.v
module Anding(
  output [3:0] s,
  input [3:0] a,
  input [3:0] b
);


  and #2 AND0 (s[0], a[0], b[0]);
  and #2 AND1 (s[1], a[1], b[1]);
  and #2 AND2 (s[2], a[2], b[2]);
  and #2 AND3 (s[3], a[3], b[3]);

endmodule

verilog files/Comparator.v
module Comparator(
    output [3:0] y,
    input [3:0] a,
    input [3:0] b
    
);

wire x3, x2, x1, x0, e, b1, ga, gb, ya3, ya2, ya1, ya0, yb3, yb2, yb1, yb0;
wire bn1,bn2,bn3,bn0;
wire an1,an2,an3,an0;


//equality check
xnor(x3,a[3],b[3]);
xnor(x2,a[2],b[2]);
xnor(x1,a[1],b[1]);
xnor(x0,a[0],b[0]);

//checking for equality condition

and(e,x3,x2,x1,x0);

//checking for A greater than B 
//negating b
not(bn3,b[3]);
not(bn2,b[2]);
not(bn1,b[1]);
not(bn0,b[0]);

//using and to check the bits of a and b
and(ya3,a[3],bn3);
and(ya2,a[2],bn2,x3);
and(ya1,a[1],bn1,x3,x2);
and(ya0,a[0],bn0,x3,x2,x1);

//or gate
or(ga,ya3,ya2,ya1,ya0);

//chcking for B greater than A
//negating the value of a
not(an3,a[3]);
not(an2,a[2]);
not(an1,a[1]);
not(an0,a[0]);

//using and to check every bit of the a and b
and(yb3,b[3],an3);
and(yb2,b[2],an2,x3);
and(yb1,b[1],an1,x3,x2);
and(yb0,b[0],an0,x3,x2,x1);

//to check if b is greater
or(gb,yb3,yb2,yb1,yb0);

    assign y = {1'b0,ga,gb,e};


endmodule

verilog files/FullAdder.v

module FullAdder(
    output s,
    output cout,
    input a,
    input b,
    input c
);

  wire h1, h2, h3,b1;

  // Expression for Sum
  xor #(1) XOR1 (h1, a, b); 
  xor #(1) XOR2 ( s, h1, c);
  
  // Expression for Cout
  and #(1) AND1 (h3, h1, c);
  and #(1) AND2 (h2, a, b);
  or #(1) OR1 (cout, h3, h2);

endmodule

verilog files/sub.v
module Sub(
    output [3:0] s2,
    output ctrl,
    input [3:0] a,
    input [3:0] b
);
  //first Full Adder
  wire [3:0] s;
  wire c1, c2, c3;
  wire cout1;
  wire b3, b2, b1, b0;

  //for second full adder
  wire [3:0] s1;
  wire ctrl;
  wire k1,k2,k3,k0;
  wire cout2;

  //negation of b 
  xor #(1) NOT3 (b3, 1'b1, b[3]);
  xor #(1) NOT2 (b2, 1'b1, b[2]);
  xor #(1) NOT1 (b1, 1'b1, b[1]);
  xor #(1) NOT0 (b0, 1'b1, b[0]);

  //Full Adder 1
  FullAdder Ad10 (s[0], c1, a[0], b0, 1'b1);
  FullAdder Ad11 (s[1], c2, a[1], b1, c1);
  FullAdder Ad12 (s[2], c3, a[2], b2, c2);
  FullAdder Ad13 (s[3], cout1, a[3], b3, c3);

  //Negate of cout

  not #(1) NOTCout (ctrl, cout1);

  //XOR GAtes for the second full adder
  xor #(1) NOT4 (s1[3], ctrl, s[3]);
  xor #(1) NOT5 (s1[2], ctrl, s[2]);
  xor #(1) NOT6 (s1[1], ctrl, s[1]);
  xor #(1) NOT7 (s1[0], ctrl, s[0]);

  //Full Adder 2

  FullAdder Ad20 (s2[0], k0, 1'b0, s1[0], ctrl);
  FullAdder Ad21 (s2[1], k1, 1'b0, s1[1], k0);
  FullAdder Ad22 (s2[2], k2, 1'b0, s1[2], k1);
  FullAdder Ad23 (s2[3], cout2, 1'b0, s1[3], k2);


endmodule

verilog files/Adder.v
module Adder(
    output [3:0] s,
    output cout,
    input [3:0] a,
    input [3:0] b
);

  wire c1, c2, c3;
  FullAdder A0 (s[0], c1, a[0], b[0], 1'b0);
  FullAdder A1 (s[1], c2, a[1], b[1], c1);
  FullAdder A2 (s[2], c3, a[2], b[2], c2);
  FullAdder A3 (s[3], cout, a[3], b[3], c3);

endmodule

verilog files/Enable.v
module Enable(
    output [3:0] c,
    output [3:0] d,
    input e,
    input [3:0] a,
    input [3:0] b
);

and #(1) EnableAND1 (c[0], e, a[0]);
and #(1) EnableAND2 (c[1], e, a[1]);
and #(1) EnableAND3 (c[2], e, a[2]);
and #(1) EnableAND4 (c[3], e, a[3]);

and #(1) EnableAND5 (d[0], e, b[0]);
and #(1) EnableAND6 (d[1], e, b[1]);
and #(1) EnableAND7 (d[2], e, b[2]);
and #(1) EnableAND8 (d[3], e, b[3]);
endmodule

verilog files/Decoder.v
module decoder(
output [3:0] y0,
output [3:0] y1,
output [3:0] y2,
output [3:0] y3,
output cout,
output sign,
input [1:0] s,
input [3:0] a,
input [3:0] b
);


wire cout;
wire sign;

//the Input signal from the output Decoder and block
wire [3:0] a0;
wire [3:0] b0;
wire [3:0] a1;
wire [3:0] b1;
wire [3:0] a2;
wire [3:0] b2;
wire [3:0] a3;
wire [3:0] b3;

//enabling signal
wire d0, d1, d2, d3;

//negating select lines
wire s1n, s0n;
not (s1n, s[1]);
not (s0n, s[0]);

//decoder and block 
and #(1) D0 (d0, s1n, s0n);
and #(1) D1 (d1, s1n, s[0]);
and #(1) D2 (d2, s[1], s0n);
and #(1) D3 (d3, s[1], s[0]);

//calling enable block with the input of decoder and block
Enable #(1) en0 (a0,b0,d0,a,b);
Enable #(1) en1 (a1,b1,d1,a,b);
Enable #(1) en2 (a2,b2,d2,a,b);
Enable #(1) en3 (a3,b3,d3,a,b);

//calling the the arthematic mdules
Adder  mod0 (y0, cout, a0, b0);
Sub  mod1 (y1, sign, a1, b1);
Comparator  mod2 (y2, a2, b2);
Anding  mod3 (y3, a3, b3);

    
endmodule

verilog files/Decoder.tb.v
`timescale 1ns / 1ps

module tb_decoder;
    reg [3:0] A;
    reg [3:0] B;
    reg [1:0] S;
    wire cout;
    wire sign;
    wire [3:0] y0, y1, y2, y3;
    

    decoder UUT(
        .y0(y0),
        .y1(y1),
        .y2(y2),
        .y3(y3),
        .cout(cout),
        .sign(sign),
        .s(S),
        .a(A),
        .b(B));

    // Initialize inputs
    initial begin
        $dumpfile("decoder.vcd");
        $dumpvars(0, UUT);
        
        A = 4'b0111; // Input A
        B = 4'b1110; // Input B
        
        //select lines

        S = 2'b00;   // Select bits for Decoder

        #50;
        $display("S = %b, A = %b, B = %b, carry = %b Y0 = %b, Y1 = %b, Y2 = %b, Y3 = %b", S, A, B, cout, y0, y1, y2, y3);

        // Change select bits for different outputs
        S = 2'b01;   // Change select bits for different outputs
        #50;
        $display("S = %b, A = %b, B = %b, Y0 = %b, sign = %b Y1 = %b, Y2 = %b, Y3 = %b", S, A, B, y0, sign, y1, y2, y3);

        S = 2'b10;
        #50;
        $display("S = %b, A = %b, B = %b, Y0 = %b, Y1 = %b, {0,ga,gb,e} Y2 = %b, Y3 = %b", S, A, B, y0, y1, y2, y3);

        S = 2'b11;
        #50;
        $display("S = %b, A = %b, B = %b, Y0 = %b, Y1 = %b, Y2 = %b, Y3 = %b", S, A, B, y0, y1, y2, y3);

        // Finish simulation
        $finish;
    end
endmodule

verilog files/decoder.vcd
$date
	Thu Nov 16 19:18:35 2023
$end
$version
	Icarus Verilog
$end
$timescale
	1ps
$end
$scope module tb_decoder $end
$scope module UUT $end
$var wire 4 ! a [3:0] $end
$var wire 4 " a0 [3:0] $end
$var wire 4 # a1 [3:0] $end
$var wire 4 $ a2 [3:0] $end
$var wire 4 % a3 [3:0] $end
$var wire 4 & b [3:0] $end
$var wire 4 ' b0 [3:0] $end
$var wire 4 ( b1 [3:0] $end
$var wire 4 ) b2 [3:0] $end
$var wire 4 * b3 [3:0] $end
$var wire 1 + cout $end
$var wire 1 , d0 $end
$var wire 1 - d1 $end
$var wire 1 . d2 $end
$var wire 1 / d3 $end
$var wire 2 0 s [1:0] $end
$var wire 1 1 s0n $end
$var wire 1 2 s1n $end
$var wire 1 3 sign $end
$var wire 4 4 y0 [3:0] $end
$var wire 4 5 y1 [3:0] $end
$var wire 4 6 y2 [3:0] $end
$var wire 4 7 y3 [3:0] $end
$scope module en0 $end
$var wire 4 8 a [3:0] $end
$var wire 4 9 b [3:0] $end
$var wire 4 : c [3:0] $end
$var wire 4 ; d [3:0] $end
$var wire 1 , e $end
$upscope $end
$scope module en1 $end
$var wire 4 < a [3:0] $end
$var wire 4 = b [3:0] $end
$var wire 4 > c [3:0] $end
$var wire 4 ? d [3:0] $end
$var wire 1 - e $end
$upscope $end
$scope module en2 $end
$var wire 4 @ a [3:0] $end
$var wire 4 A b [3:0] $end
$var wire 4 B c [3:0] $end
$var wire 4 C d [3:0] $end
$var wire 1 . e $end
$upscope $end
$scope module en3 $end
$var wire 4 D a [3:0] $end
$var wire 4 E b [3:0] $end
$var wire 4 F c [3:0] $end
$var wire 4 G d [3:0] $end
$var wire 1 / e $end
$upscope $end
$scope module mod0 $end
$var wire 4 H a [3:0] $end
$var wire 4 I b [3:0] $end
$var wire 1 J c1 $end
$var wire 1 K c2 $end
$var wire 1 L c3 $end
$var wire 1 + cout $end
$var wire 4 M s [3:0] $end
$scope module A0 $end
$var wire 1 N a $end
$var wire 1 O b $end
$var wire 1 P c $end
$var wire 1 J cout $end
$var wire 1 Q h1 $end
$var wire 1 R h2 $end
$var wire 1 S h3 $end
$var wire 1 T s $end
$upscope $end
$scope module A1 $end
$var wire 1 U a $end
$var wire 1 V b $end
$var wire 1 J c $end
$var wire 1 K cout $end
$var wire 1 W h1 $end
$var wire 1 X h2 $end
$var wire 1 Y h3 $end
$var wire 1 Z s $end
$upscope $end
$scope module A2 $end
$var wire 1 [ a $end
$var wire 1 \ b $end
$var wire 1 K c $end
$var wire 1 L cout $end
$var wire 1 ] h1 $end
$var wire 1 ^ h2 $end
$var wire 1 _ h3 $end
$var wire 1 ` s $end
$upscope $end
$scope module A3 $end
$var wire 1 a a $end
$var wire 1 b b $end
$var wire 1 L c $end
$var wire 1 + cout $end
$var wire 1 c h1 $end
$var wire 1 d h2 $end
$var wire 1 e h3 $end
$var wire 1 f s $end
$upscope $end
$upscope $end
$scope module mod1 $end
$var wire 4 g a [3:0] $end
$var wire 4 h b [3:0] $end
$var wire 1 i b0 $end
$var wire 1 j b1 $end
$var wire 1 k b2 $end
$var wire 1 l b3 $end
$var wire 1 m c1 $end
$var wire 1 n c2 $end
$var wire 1 o c3 $end
$var wire 1 p cout1 $end
$var wire 1 q cout2 $end
$var wire 1 3 ctrl $end
$var wire 1 r k0 $end
$var wire 1 s k1 $end
$var wire 1 t k2 $end
$var wire 4 u s [3:0] $end
$var wire 4 v s1 [3:0] $end
$var wire 4 w s2 [3:0] $end
$scope module Ad10 $end
$var wire 1 x a $end
$var wire 1 i b $end
$var wire 1 y c $end
$var wire 1 m cout $end
$var wire 1 z h1 $end
$var wire 1 { h2 $end
$var wire 1 | h3 $end
$var wire 1 } s $end
$upscope $end
$scope module Ad11 $end
$var wire 1 ~ a $end
$var wire 1 j b $end
$var wire 1 m c $end
$var wire 1 n cout $end
$var wire 1 !" h1 $end
$var wire 1 "" h2 $end
$var wire 1 #" h3 $end
$var wire 1 $" s $end
$upscope $end
$scope module Ad12 $end
$var wire 1 %" a $end
$var wire 1 k b $end
$var wire 1 n c $end
$var wire 1 o cout $end
$var wire 1 &" h1 $end
$var wire 1 '" h2 $end
$var wire 1 (" h3 $end
$var wire 1 )" s $end
$upscope $end
$scope module Ad13 $end
$var wire 1 *" a $end
$var wire 1 l b $end
$var wire 1 o c $end
$var wire 1 p cout $end
$var wire 1 +" h1 $end
$var wire 1 ," h2 $end
$var wire 1 -" h3 $end
$var wire 1 ." s $end
$upscope $end
$scope module Ad20 $end
$var wire 1 /" a $end
$var wire 1 0" b $end
$var wire 1 3 c $end
$var wire 1 r cout $end
$var wire 1 1" h1 $end
$var wire 1 2" h2 $end
$var wire 1 3" h3 $end
$var wire 1 4" s $end
$upscope $end
$scope module Ad21 $end
$var wire 1 5" a $end
$var wire 1 6" b $end
$var wire 1 r c $end
$var wire 1 s cout $end
$var wire 1 7" h1 $end
$var wire 1 8" h2 $end
$var wire 1 9" h3 $end
$var wire 1 :" s $end
$upscope $end
$scope module Ad22 $end
$var wire 1 ;" a $end
$var wire 1 <" b $end
$var wire 1 s c $end
$var wire 1 t cout $end
$var wire 1 =" h1 $end
$var wire 1 >" h2 $end
$var wire 1 ?" h3 $end
$var wire 1 @" s $end
$upscope $end
$scope module Ad23 $end
$var wire 1 A" a $end
$var wire 1 B" b $end
$var wire 1 t c $end
$var wire 1 q cout $end
$var wire 1 C" h1 $end
$var wire 1 D" h2 $end
$var wire 1 E" h3 $end
$var wire 1 F" s $end
$upscope $end
$upscope $end
$scope module mod2 $end
$var wire 4 G" a [3:0] $end
$var wire 1 H" an0 $end
$var wire 1 I" an1 $end
$var wire 1 J" an2 $end
$var wire 1 K" an3 $end
$var wire 4 L" b [3:0] $end
$var wire 1 M" bn0 $end
$var wire 1 N" bn1 $end
$var wire 1 O" bn2 $end
$var wire 1 P" bn3 $end
$var wire 1 Q" e $end
$var wire 1 R" ga $end
$var wire 1 S" gb $end
$var wire 1 T" x0 $end
$var wire 1 U" x1 $end
$var wire 1 V" x2 $end
$var wire 1 W" x3 $end
$var wire 4 X" y [3:0] $end
$var wire 1 Y" ya0 $end
$var wire 1 Z" ya1 $end
$var wire 1 [" ya2 $end
$var wire 1 \" ya3 $end
$var wire 1 ]" yb0 $end
$var wire 1 ^" yb1 $end
$var wire 1 _" yb2 $end
$var wire 1 `" yb3 $end
$upscope $end
$scope module mod3 $end
$var wire 4 a" a [3:0] $end
$var wire 4 b" b [3:0] $end
$var wire 4 c" s [3:0] $end
$upscope $end
$upscope $end
$upscope $end
$enddefinitions $end
#0
$dumpvars
bx c"
bxz b"
bzxxx a"
x`"
x_"
z^"
x]"
x\"
x["
zZ"
xY"
b0xxx X"
xW"
xV"
xU"
xT"
zS"
zR"
zQ"
xP"
xO"
xN"
xM"
bxz L"
xK"
xJ"
xI"
xH"
bzxxx G"
xF"
xE"
zD"
xC"
xB"
0A"
x@"
x?"
z>"
x="
x<"
0;"
x:"
x9"
z8"
x7"
x6"
05"
x4"
x3"
z2"
x1"
x0"
0/"
x."
x-"
x,"
x+"
z*"
x)"
x("
x'"
x&"
x%"
x$"
x#"
x""
x!"
x~
x}
x|
x{
xz
1y
xx
bx w
bx v
bx u
xt
xs
xr
xq
xp
xo
xn
xm
xl
xk
xj
xi
bxz h
bzxxx g
xf
xe
xd
xc
xb
za
x`
x_
x^
x]
x\
x[
xZ
xY
xX
xW
xV
xU
xT
zS
xR
xQ
0P
zO
xN
bx M
xL
xK
xJ
bxz I
bzxxx H
bxz G
bzxxx F
b1110 E
b111 D
bxz C
bzxxx B
b1110 A
b111 @
bxz ?
bzxxx >
b1110 =
b111 <
bxz ;
bzxxx :
b1110 9
b111 8
bx 7
b0xxx 6
bx 5
bx 4
x3
12
11
b0 0
z/
z.
z-
x,
x+
bxz *
bxz )
bxz (
bxz '
b1110 &
bzxxx %
bzxxx $
bzxxx #
bzxxx "
b111 !
$end
#1000
xS"
0]"
xR"
1M"
0\"
1K"
0*"
0O
0a
1,
0D"
0>"
08"
02"
0S
bx0 *
bx0 G
bx0 b"
b0xxx %
b0xxx F
b0xxx a"
bx0 )
bx0 C
bx0 L"
b0xxx $
b0xxx B
b0xxx G"
bx0 (
bx0 ?
bx0 h
b0xxx #
b0xxx >
b0xxx g
bx0 '
bx0 ;
bx0 I
b0xxx "
b0xxx :
b0xxx H
0/
0.
0-
#2000
0R"
0Y"
1Q"
0S"
b1 6
b1 X"
1T"
1H"
0Z"
1I"
0["
1J"
1U"
1N"
0^"
1V"
1O"
0_"
1W"
1P"
0`"
1N
1U
1[
1V
1\
1b
0x
0~
0%"
1i
0,"
0R
0d
b111 "
b111 :
b111 H
b1110 '
b1110 ;
b1110 I
b0 %
b0 F
b0 a"
b0 *
b0 G
b0 b"
b0 $
b0 B
b0 G"
b0 )
b0 C
b0 L"
b0 #
b0 >
b0 g
b0 (
b0 ?
b0 h
#3000
1Q
0W
1X
0]
1^
1c
0""
0'"
1j
1k
1l
1z
0{
0J
b0xx0 7
b0xx0 c"
#4000
1T
1K
0_
1L
1!"
1&"
1+"
0}
bx0 u
1|
0Z
bx01 4
bx01 M
0Y
b0 7
b0 c"
#5000
1`
0f
b101 4
b101 M
1e
1m
#6000
1+
0$"
bx00 u
1#"
#7000
1n
#8000
0)"
bx000 u
1("
#9000
1o
#10000
0."
b0 u
1-"
#11000
1p
#12000
03
#13000
0B"
0<"
06"
00"
b0 v
03"
#14000
0C"
0="
07"
01"
0r
#15000
0E"
0?"
04"
0:"
bx00 5
bx00 w
09"
#16000
0q
0t
0s
#17000
0F"
0@"
b0 5
b0 w
#50000
01
b1 0
#51000
0,
1-
#52000
0N
0U
0[
0V
0\
0b
1x
1~
1%"
b0 "
b0 :
b0 H
b0 '
b0 ;
b0 I
b111 #
b111 >
b111 g
b1110 (
b1110 ?
b1110 h
#53000
0Q
0X
0^
0c
0z
1{
0!"
1""
0&"
1'"
0j
0k
0l
#54000
0T
0K
0L
1f
b1100 4
b1100 M
0e
1}
0|
1$"
0#"
1)"
b111 u
0("
1!"
0""
1&"
0'"
0+"
#55000
10"
16"
1<"
b111 v
0`
0f
b0 4
b0 M
0+
0$"
1#"
0n
0)"
1("
0o
1."
b1001 u
0-"
#56000
06"
0<"
1B"
11"
17"
1="
b1001 v
1n
1)"
0("
1o
0."
b101 u
0p
#57000
1<"
0B"
07"
0="
1C"
b101 v
14"
1:"
1@"
b111 5
b111 w
0)"
1("
0o
1."
b1001 u
13
#58000
16"
00"
1="
0C"
0:"
0@"
1F"
1o
0."
b1 u
b110 v
04"
b1000 5
b1000 w
13"
#59000
1B"
b1110 v
17"
01"
1@"
0F"
b100 5
b100 w
1."
b1001 u
1r
#60000
0B"
1C"
b110 v
14"
b101 5
b101 w
03"
19"
#61000
0C"
1F"
b1101 5
b1101 w
0r
1s
#62000
0F"
1:"
09"
0@"
b11 5
b11 w
1?"
#63000
0s
1t
#64000
1@"
0?"
1F"
b1111 5
b1111 w
#65000
0t
#66000
0F"
b111 5
b111 w
#100000
02
11
b10 0
#101000
1.
0-
#102000
0Q"
1S"
b10 6
b10 X"
0T"
0H"
0I"
0J"
0N"
0O"
0W"
0P"
1`"
0x
0~
0%"
b111 $
b111 B
b111 G"
b1110 )
b1110 C
b1110 L"
b0 #
b0 >
b0 g
b0 (
b0 ?
b0 h
#103000
1z
0{
0!"
0&"
1j
1k
1l
#104000
0}
1|
0m
1$"
0#"
1)"
b1110 u
0("
1!"
1&"
1+"
#105000
10"
06"
0<"
b1 v
1m
0n
0o
0)"
1("
0."
b10 u
1-"
#106000
1<"
1B"
11"
07"
0="
b1101 v
0$"
1#"
1)"
0("
1."
b1100 u
0-"
1o
1p
#107000
16"
0<"
0B"
1="
1C"
b11 v
04"
13"
0:"
0@"
b0 5
b0 w
1n
0o
0p
0."
b100 u
1-"
03
#108000
1<"
06"
00"
17"
0="
0C"
1@"
1F"
1r
0)"
1("
1."
b1000 u
0-"
13
1p
b100 v
14"
b1101 5
b1101 w
03"
#109000
16"
10"
1="
07"
01"
0@"
0F"
19"
1o
0p
b111 v
04"
b0 5
b0 w
13"
03
0r
#110000
1B"
0<"
06"
00"
17"
11"
1@"
b100 5
b100 w
1s
0."
b0 u
1-"
13
1r
b1000 v
03"
09"
#111000
1<"
16"
10"
1C"
0="
07"
01"
0@"
b0 5
b0 w
1?"
1p
b1111 v
13"
19"
0r
0s
#112000
1="
17"
11"
1F"
14"
b1001 5
b1001 w
03"
1t
03
1r
1s
09"
0?"
#113000
0B"
0<"
06"
00"
0r
0F"
b1 5
b1 w
1E"
b0 v
19"
1?"
0s
0t
#114000
0C"
0="
07"
01"
1:"
09"
1q
1s
1t
1@"
0?"
1F"
b1111 5
b1111 w
0E"
#115000
0:"
04"
b1100 5
b1100 w
0s
0t
0q
#116000
0@"
0F"
b0 5
b0 w
#150000
01
b11 0
#151000
0.
1/
#152000
1Q"
0S"
b1 6
b1 X"
1T"
1H"
1I"
1J"
1N"
1O"
1W"
1P"
0`"
b0 $
b0 B
b0 G"
b0 )
b0 C
b0 L"
b111 %
b111 F
b111 a"
b1110 *
b1110 G
b1110 b"
#154000
b110 7
b110 c"
